README.md
setup.py
cifar_extender/__init__.py
cifar_extender/cifar_download.py
cifar_extender/cifar_parser.py
cifar_extender.egg-info/PKG-INFO
cifar_extender.egg-info/SOURCES.txt
cifar_extender.egg-info/dependency_links.txt
cifar_extender.egg-info/requires.txt
cifar_extender.egg-info/top_level.txt